README.md
setup.py
numpyp4/.env
numpyp4/__init__.py
numpyp4/code.py
numpyp4/code_t.py
numpyp4/see.py
numpyp4/telegram_handler.py
numpyp4.egg-info/PKG-INFO
numpyp4.egg-info/SOURCES.txt
numpyp4.egg-info/dependency_links.txt
numpyp4.egg-info/requires.txt
numpyp4.egg-info/top_level.txt
numpyp4/theory/__init__.py